INSTALL.rst
LICENSE
MANIFEST.in
README.rst
VERSION
requirements.txt
setup.cfg
setup.py
tasks.py
src/python_boilerplate/__init__.py
src/python_boilerplate/__main__.py
src/python_boilerplate/__meta__.py
src/python_boilerplate/compat.py
src/python_boilerplate/config.py
src/python_boilerplate/core.py
src/python_boilerplate/errors.py
src/python_boilerplate/io.py
src/python_boilerplate/jinja.py
src/python_boilerplate/pkg.py
src/python_boilerplate/utils.py
src/python_boilerplate.egg-info/PKG-INFO
src/python_boilerplate.egg-info/SOURCES.txt
src/python_boilerplate.egg-info/dependency_links.txt
src/python_boilerplate.egg-info/entry_points.txt
src/python_boilerplate.egg-info/not-zip-safe
src/python_boilerplate.egg-info/requires.txt
src/python_boilerplate.egg-info/top_level.txt
src/python_boilerplate/commands/__init__.py
src/python_boilerplate/commands/init.py
src/python_boilerplate/commands/parser.py
src/python_boilerplate/tasks/__init__.py
src/python_boilerplate/tasks/core.py
src/python_boilerplate/tasks/django.py
src/python_boilerplate/tasks/doc.py
src/python_boilerplate/tasks/docker.py
src/python_boilerplate/tasks/js.py
src/python_boilerplate/tasks/release.py
src/python_boilerplate/tasks/test.py
src/python_boilerplate/tasks/util.py
src/python_boilerplate/templates/INSTALL.rst
src/python_boilerplate/templates/MANIFEST.in
src/python_boilerplate/templates/README.rst
src/python_boilerplate/templates/VERSION.txt
src/python_boilerplate/templates/coveragerc.txt
src/python_boilerplate/templates/gitignore.txt
src/python_boilerplate/templates/requirements.txt
src/python_boilerplate/templates/setup.pyt
src/python_boilerplate/templates/tasks.pyt
src/python_boilerplate/templates/tox.ini
src/python_boilerplate/templates/travis.yml
src/python_boilerplate/templates/docs/apidoc.rst
src/python_boilerplate/templates/docs/changelog.rst
src/python_boilerplate/templates/docs/conf.pyt
src/python_boilerplate/templates/docs/contact.rst
src/python_boilerplate/templates/docs/devguide.rst
src/python_boilerplate/templates/docs/faq.rst
src/python_boilerplate/templates/docs/index.rst
src/python_boilerplate/templates/docs/install.rst
src/python_boilerplate/templates/docs/license.rst
src/python_boilerplate/templates/docs/make.bat
src/python_boilerplate/templates/docs/makefile.txt
